odoo/addons/shopinvader_api_sale/README.rst
odoo/addons/shopinvader_api_sale/__init__.py
odoo/addons/shopinvader_api_sale/__manifest__.py
odoo/addons/shopinvader_api_sale/schemas.py
odoo/addons/shopinvader_api_sale/i18n/shopinvader_api_sale.pot
odoo/addons/shopinvader_api_sale/readme/CONTRIBUTORS.rst
odoo/addons/shopinvader_api_sale/readme/DESCRIPTION.rst
odoo/addons/shopinvader_api_sale/routers/__init__.py
odoo/addons/shopinvader_api_sale/routers/sale_lines.py
odoo/addons/shopinvader_api_sale/routers/sales.py
odoo/addons/shopinvader_api_sale/static/description/index.html
odoo/addons/shopinvader_api_sale/tests/__init__.py
odoo/addons/shopinvader_api_sale/tests/test_shopinvader_sale_api.py
odoo_addon_shopinvader_api_sale-16.0.1.2.0.dist-info/METADATA
odoo_addon_shopinvader_api_sale-16.0.1.2.0.dist-info/WHEEL
odoo_addon_shopinvader_api_sale-16.0.1.2.0.dist-info/top_level.txt
odoo_addon_shopinvader_api_sale-16.0.1.2.0.dist-info/RECORD
